.gitignore
LICENSE
MANIFEST.in
README.rst
setup.py
example/__init__.py
example/babel.ini
example/cli.py
example/config.py
example/extensions.py
example/forms.py
example/models.py
example/data/browsers.json
example/data/menu.json
example/data/users.json
example/routes/__init__.py
example/routes/auth.py
example/routes/demo.py
example/routes/site.py
example/templates/includes/second_sidebar.html
example/templates/pages/layouts_options.html
example/templates/pages/widgets.html
example/templates/pages/UI/general.html
example/templates/pages/tables/data.html
example/templates/pages/tables/simple.html
example/translations/messages.pot
example/translations/ru/LC_MESSAGES/messages.mo
example/translations/ru/LC_MESSAGES/messages.po
example/translations/uk_UA/LC_MESSAGES/messages.mo
example/translations/uk_UA/LC_MESSAGES/messages.po
flask_adminlte_full/__init__.py
flask_adminlte_full/forms.py
flask_adminlte_full.egg-info/PKG-INFO
flask_adminlte_full.egg-info/SOURCES.txt
flask_adminlte_full.egg-info/dependency_links.txt
flask_adminlte_full.egg-info/requires.txt
flask_adminlte_full.egg-info/top_level.txt
flask_adminlte_full/static/dist/css/adminlte.css
flask_adminlte_full/static/dist/css/adminlte.css.map
flask_adminlte_full/static/dist/css/adminlte.min.css
flask_adminlte_full/static/dist/css/adminlte.min.css.map
flask_adminlte_full/static/dist/css/alt/adminlte.components.css
flask_adminlte_full/static/dist/css/alt/adminlte.components.css.map
flask_adminlte_full/static/dist/css/alt/adminlte.components.min.css
flask_adminlte_full/static/dist/css/alt/adminlte.components.min.css.map
flask_adminlte_full/static/dist/css/alt/adminlte.core.css
flask_adminlte_full/static/dist/css/alt/adminlte.core.css.map
flask_adminlte_full/static/dist/css/alt/adminlte.core.min.css
flask_adminlte_full/static/dist/css/alt/adminlte.core.min.css.map
flask_adminlte_full/static/dist/css/alt/adminlte.extra-components.css
flask_adminlte_full/static/dist/css/alt/adminlte.extra-components.css.map
flask_adminlte_full/static/dist/css/alt/adminlte.extra-components.min.css
flask_adminlte_full/static/dist/css/alt/adminlte.extra-components.min.css.map
flask_adminlte_full/static/dist/css/alt/adminlte.pages.css
