Metadata-Version: 1.1
Name: flask-adminlte-full
Version: 0.2.0
Summary: An extension for Flask that integrates the AdminLTE template with most of the features.
Home-page: https://github.com/kyzima-spb/flask-adminlte-full
Author: Kirill Vercetti
Author-email: office@kyzima-spb.com
License: MIT
Keywords: adminlte adminlte3 flask templating html
Platform: UNKNOWN
Classifier: Programming Language :: Python :: 3 :: Only
Classifier: License :: OSI Approved :: MIT License
Classifier: Operating System :: OS Independent
Classifier: Environment :: Web Environment
Classifier: Framework :: Flask
Classifier: Development Status :: 3 - Alpha
Classifier: Topic :: Internet :: WWW/HTTP
Classifier: Topic :: Internet :: WWW/HTTP :: Dynamic Content
